{"advertisement_analysis":{"visual_content":{"key_characters":[],"setting":{"location":["graphic design"],"notable_elements":[],"presence_of_text":["Yes"],"graphic_design":["Yes"]}},"thematic_analysis":{"overarching_issue":["education and housing"],"central_themes":["support for students","housing investment","financial relief"],"persuasive_techniques":["factual appeal","promise of benefits"],"issue_portrayal":["supportive of student needs"],"ad_goal":["policy advocacy"]},"keyword_analysis":{"keywords":["student housing","construction investment","student loan interest","non-inclusion in mortgage"],"political_relevance":{"education":["high"],"housing":["high"],"economy":["high"],"youth policy":["high"]}},"content":{"text":["Flink meer geld voor de bouw van studentenwoningen. En vaste huurcontracten moeten standaard zijn, ook voor studentenkamers. Voor studenten die onder het leenstelsel vielen, willen we de rente vastzetten op 0%. We investeren flink meer geld in de bouw van studentenwoningen. We willen dat een studielening niet meetelt bij een hypotheekaanvraag. Stem voor nieuwe energie voor Nederland. Stem 22 november D66."],"claims":["Increased funding for student housing","Fixed rental contracts for students","Interest rate fix for student loans","Student loan exclusion from mortgage considerations"],"attacks":[],"issues_discussed":["Student housing","Educational finance","Housing market"],"pledges":["Commitment to improve student living and financial conditions"]},"sentiment_analysis":{"overall_sentiment":["positive"],"contributing_elements":{"visuals":["clear"],"themes":["optimistic"],"text":["promising"]}}}}
