{"advertisement_analysis":{"visual_content":{"key_characters":[{"character_id":1,"features":{"attire":"none","age":"none","gender":"none"},"actions":"none","likely_name":""}],"setting":{"location":["undefined"],"notable_elements":[],"presence_of_text":["Yes"],"graphic_design":["Yes"]}},"thematic_analysis":{"overarching_issue":["economy"],"central_themes":["fuel and energy costs","cost reduction"],"persuasive_techniques":["rhetorical question","appeal to common sense"],"issue_portrayal":["suggestive of a solution"],"ad_goal":["persuasion"]},"keyword_analysis":{"keywords":["duurste benzine","energie","Europa","goedkoper","JA21"],"political_relevance":{"economy":["high"],"energy":["high"],"policy":["high"]}},"content":{"text":["De duurste benzine en energie van Europa, dat kan toch veel goedkoper? JA21"],"claims":["Claiming the possibility of cheaper fuel and energy in Europe"],"attacks":["Implicit criticism of current energy prices"],"issues_discussed":["High fuel and energy costs"],"pledges":["Suggesting JA21 could achieve cheaper prices"]},"sentiment_analysis":{"overall_sentiment":["neutral to negative"],"contributing_elements":{"visuals":["bold colors and text"],"themes":["economic concern"],"text":["challenging"]}}}}
